hello_linker/__init__.py
hello_linker/kaminet.py
hello_linker-0.5.dist-info/METADATA
hello_linker-0.5.dist-info/WHEEL
hello_linker-0.5.dist-info/top_level.txt
hello_linker-0.5.dist-info/RECORD
