Metadata-Version: 2.1
Name: hello-linker
Version: 0.5
Summary: A Python Library For Kamibot
Home-page: UNKNOWN
Author: devdio
Author-email: kei.devdio@gmail.com
License: UNKNOWN
Keywords: Kamibot,KamiblockAI,Robot,KamiLink
Platform: UNKNOWN
Classifier: Operating System :: Microsoft :: Windows
Classifier: Programming Language :: Python :: 3.7
Classifier: Programming Language :: Python :: 3.8
Requires-Python: >=3.7
Requires-Dist: uuid
Requires-Dist: python-engineio (==3.14.2)
Requires-Dist: python-socketio (==4.6.0)
Requires-Dist: requests (==2.27.1)
Requires-Dist: pynput (==1.7.6)
